{
  "generated_at": "2026-06-10T09:34:12.302571Z",
  "window_days": 7,
  "max_rank": 50,
  "new_only": true,
  "items": [
    {
      "asin": "B09CQ1XZRH",
      "title": "Awesome Like My Daughters Mom Dad Mother's Day Father's Day T-Shirt",
      "link": "https://www.amazon.com/Awesome-Daughters-Mothers-Day-Fathers/dp/B09CQ1XZRH/ref=zg_bs_g_9056987011_d_sccl_25/131-3647808-4071947",
      "current_rank": 25,
      "category_url": "https://www.amazon.com/Best-Sellers-Men%27s-Novelty-T-Shirts/zgbs/fashion/9056987011",
      "days_seen": 1,
      "first_seen": "2026-06-10T09:34:12.200661Z",
      "keywords": [
        "awesome",
        "like",
        "daughters",
        "mom",
        "dad",
        "mother's",
        "day",
        "father's"
      ],
      "idea_prompt": "Create an original, text-forward T-shirt design around: awesome, like, daughters, mom, dad, mother's, day, father's. Use clear fonts and simple iconography. Avoid trademarks."
    },
    {
      "asin": "B0DYVRD2D4",
      "title": "Grunt Style American 1776 Flag - Patriotic Graphic Tee, Men's Short Sleeve T-Shirt",
      "link": "https://www.amazon.com/Grunt-Style-T-Shirt-Midnight-Large/dp/B0DYVRD2D4/ref=zg_bs_g_9056987011_d_sccl_30/131-3647808-4071947",
      "current_rank": 30,
      "category_url": "https://www.amazon.com/Best-Sellers-Men%27s-Novelty-T-Shirts/zgbs/fashion/9056987011",
      "days_seen": 1,
      "first_seen": "2026-06-10T09:34:12.200661Z",
      "keywords": [
        "grunt",
        "style",
        "american",
        "1776",
        "flag",
        "patriotic"
      ],
      "idea_prompt": "Create an original, text-forward T-shirt design around: grunt, style, american, 1776, flag, patriotic. Use clear fonts and simple iconography. Avoid trademarks."
    }
  ]
}